petcode/__init__.py
petcode/create_and_read.py
petcode/effect.py
petcode-1.1.0.dist-info/WHEEL
petcode-1.1.0.dist-info/METADATA
petcode-1.1.0.dist-info/RECORD
