Metadata-Version: 2.3
Name: petcode
Version: 1.1.0
Summary: PetCode SDK for Python
Requires-Dist: seerbp-petcode-protocolbuffers-python==33.2.0.1.20260110152342+c9e05318fd42
Requires-Python: >=3.10
